python_sinal2-0.2.2.dist-info/DESCRIPTION.rst
python_sinal2-0.2.2.dist-info/METADATA
python_sinal2-0.2.2.dist-info/RECORD
python_sinal2-0.2.2.dist-info/WHEEL
python_sinal2-0.2.2.dist-info/entry_points.txt
python_sinal2-0.2.2.dist-info/metadata.json
python_sinal2-0.2.2.dist-info/top_level.txt
sinal2/__init__.py
sinal2/cli.py
sinal2/runner.py
sinal2/sinal2.py
