Metadata-Version: 2.0
Name: python-sinal2
Version: 0.2.2
Summary: Sina Level2 Data Fetcher
Home-page: http://github.com/observerss/sinal2
Author: Jingchao Hu
Author-email: jingchaohu@gmail.com
License: UNKNOWN
Platform: UNKNOWN
Classifier: Development Status :: 4 - Beta
Classifier: Intended Audience :: Developers
Classifier: License :: OSI Approved :: MIT License
Classifier: Programming Language :: Python :: 3
Requires-Python: >=3.5
Requires-Dist: click
Requires-Dist: gevent
Requires-Dist: gipc
Requires-Dist: requests
Requires-Dist: tqdm
Requires-Dist: websocket-client
Requires-Dist: wsaccel
